drawy/__init__.py
drawy/drawer.py
drawy-1.0.2.1.dist-info/LICENSE
drawy-1.0.2.1.dist-info/METADATA
drawy-1.0.2.1.dist-info/WHEEL
drawy-1.0.2.1.dist-info/top_level.txt
drawy-1.0.2.1.dist-info/RECORD
