Metadata-Version: 2.1
Name: drawy
Version: 1.0.2.1
Summary: Easily create interactive graphical applications
Home-page: https://github.com/NextLight/drawy
Author: Samuele Turci
Classifier: Programming Language :: Python :: 3
Classifier: License :: OSI Approved :: MIT License
Classifier: Operating System :: OS Independent
Requires-Python: >=3.6
License-File: LICENSE
Requires-Dist: skia-python (>=87.0)
Requires-Dist: glfw (>=2.0.0)
